odoo/addons/shopinvader_image/README.rst
odoo/addons/shopinvader_image/__init__.py
odoo/addons/shopinvader_image/__manifest__.py
odoo/addons/shopinvader_image/hooks.py
odoo/addons/shopinvader_image/data/ir_export_category.xml
odoo/addons/shopinvader_image/data/ir_export_product.xml
odoo/addons/shopinvader_image/data/shopinvader_image_resize.xml
odoo/addons/shopinvader_image/demo/backend_demo.xml
odoo/addons/shopinvader_image/demo/product_image_relation_demo.xml
odoo/addons/shopinvader_image/demo/product_product_image_relation_demo.xml
odoo/addons/shopinvader_image/demo/storage_file_demo.xml
odoo/addons/shopinvader_image/demo/storage_image_demo.xml
odoo/addons/shopinvader_image/demo/storage_image_product_image_tag_demo.xml
odoo/addons/shopinvader_image/models/__init__.py
odoo/addons/shopinvader_image/models/shopinvader_backend.py
odoo/addons/shopinvader_image/models/shopinvader_category.py
odoo/addons/shopinvader_image/models/shopinvader_image_mixin.py
odoo/addons/shopinvader_image/models/shopinvader_image_resize.py
odoo/addons/shopinvader_image/models/shopinvader_variant.py
odoo/addons/shopinvader_image/readme/CONFIGURE.rst
odoo/addons/shopinvader_image/readme/CONTRIBUTORS.rst
odoo/addons/shopinvader_image/readme/DESCRIPTION.rst
odoo/addons/shopinvader_image/readme/HISTORY.rst
odoo/addons/shopinvader_image/readme/INSTALL.rst
odoo/addons/shopinvader_image/security/ir.model.access.csv
odoo/addons/shopinvader_image/services/__init__.py
odoo/addons/shopinvader_image/services/abstract_sale.py
odoo/addons/shopinvader_image/static/description/index.html
odoo/addons/shopinvader_image/static/img/2be1238822f7edbc3b3c5f64c6e12f36ec84c861_chathm001gry_uk_thelma_dining_chairs_oak_grey07-524.jpg
odoo/addons/shopinvader_image/static/img/51gnjksrxml_sl1024_-497.jpg
odoo/addons/shopinvader_image/static/img/5c7f91a29eb6294768ad59bbce80ed04fcaff33d_chathm001gry_uk_thelma_dining_chairs_oak_grey02-515.jpg
odoo/addons/shopinvader_image/static/img/61kcwirwmjl_sl1500_-289.jpg
odoo12_addon_shopinvader_image-12.0.1.1.0.dist-info/METADATA
odoo12_addon_shopinvader_image-12.0.1.1.0.dist-info/WHEEL
odoo12_addon_shopinvader_image-12.0.1.1.0.dist-info/top_level.txt
odoo12_addon_shopinvader_image-12.0.1.1.0.dist-info/RECORD
