Metadata-Version: 2.1
Name: odoo12-addon-shopinvader-image
Version: 12.0.1.1.0
Summary: Add the export of Image for Shopinvader
Home-page: https://github.com/shopinvader/odoo-shopinvader
Author: Akretion
License: AGPL-3
Platform: UNKNOWN
Classifier: Programming Language :: Python
Classifier: Framework :: Odoo
Classifier: License :: OSI Approved :: GNU Affero General Public License v3
Requires-Python: >=3.5
Requires-Dist: odoo12-addon-shopinvader
Requires-Dist: odoo12-addon-storage-image-product
Requires-Dist: odoo (<12.1dev,>=12.0a)
